<?xml version="1.0" encoding="utf-8"?>
<ArrayOfObjTrainPositions xmlns:xsi="http://www.w3.org/2001/XMLSchema-instance" xmlns:xsd="http://www.w3.org/2001/XMLSchema" xmlns="http://api.irishrail.ie/realtime/">
  <objTrainPositions>
    <TrainStatus>N</TrainStatus>
    <TrainLatitude>51.8491</TrainLatitude>
    <TrainLongitude>-8.29956</TrainLongitude>
    <TrainCode>P501</TrainCode>
    <TrainDate>03 Oct 2025</TrainDate>
    <PublicMessage>P501\nCobh to Cork\nExpected Departure 06:00</PublicMessage>
    <Direction>To Cork</Direction>
  </objTrainPositions>
  <objTrainPositions>
    <TrainStatus>N</TrainStatus>
    <TrainLatitude>52.2667</TrainLatitude>
    <TrainLongitude>-7.1183</TrainLongitude>
    <TrainCode>A503</TrainCode>
    <TrainDate>03 Oct 2025</TrainDate>
    <PublicMessage>A503\nWaterford to Dublin Heuston\nExpected Departure 05:55</PublicMessage>
    <Direction>To Dublin Heuston</Direction>
  </objTrainPositions>
  <objTrainPositions>
    <TrainStatus>N</TrainStatus>
    <TrainLatitude>52.6587</TrainLatitude>
    <TrainLongitude>-8.62397</TrainLongitude>
    <TrainCode>A780</TrainCode>
    <TrainDate>03 Oct 2025</TrainDate>
    <PublicMessage>A780\nLimerick to Galway\nExpected Departure 05:55</PublicMessage>
    <Direction>To Galway</Direction>
  </objTrainPositions>
  <objTrainPositions>
    <TrainStatus>N</TrainStatus>
    <TrainLatitude>53.1855</TrainLatitude>
    <TrainLongitude>-6.80807</TrainLongitude>
    <TrainCode>P400</TrainCode>
    <TrainDate>03 Oct 2025</TrainDate>
    <PublicMessage>P400\nNewbridge to Grand Canal Dock\nExpected Departure 06:04</PublicMessage>
    <Direction>Northbound</Direction>
  </objTrainPositions>
  <objTrainPositions>
    <TrainStatus>N</TrainStatus>
    <TrainLatitude>53.3464</TrainLatitude>
    <TrainLongitude>-6.29461</TrainLongitude>
    <TrainCode>A200</TrainCode>
    <TrainDate>03 Oct 2025</TrainDate>
    <PublicMessage>A200\nDublin Heuston to Cork\nExpected Departure 06:00</PublicMessage>
    <Direction>To Cork</Direction>
  </objTrainPositions>
  <objTrainPositions>
    <TrainStatus>N</TrainStatus>
    <TrainLatitude>53.3531</TrainLatitude>
    <TrainLongitude>-6.24591</TrainLongitude>
    <TrainCode>E200</TrainCode>
    <TrainDate>03 Oct 2025</TrainDate>
    <PublicMessage>E200\nDublin Connolly to Bray\nExpected Departure 06:03</PublicMessage>
    <Direction>Southbound</Direction>
  </objTrainPositions>
  <objTrainPositions>
    <TrainStatus>N</TrainStatus>
    <TrainLatitude>53.7243</TrainLatitude>
    <TrainLongitude>-7.79574</TrainLongitude>
    <TrainCode>P652</TrainCode>
    <TrainDate>03 Oct 2025</TrainDate>
    <PublicMessage>P652\nLongford to Dublin Pearse\nExpected Departure 06:09</PublicMessage>
    <Direction>Southbound</Direction>
  </objTrainPositions>
  <objTrainPositions>
    <TrainStatus>N</TrainStatus>
    <TrainLatitude>54.6123</TrainLatitude>
    <TrainLongitude>-5.91744</TrainLongitude>
    <TrainCode>A101</TrainCode>
    <TrainDate>03 Oct 2025</TrainDate>
    <PublicMessage>A101\nBelfast to Dublin Connolly\nExpected Departure 06:00</PublicMessage>
    <Direction>Southbound</Direction>
  </objTrainPositions>
  <objTrainPositions>
    <TrainStatus>R</TrainStatus>
    <TrainLatitude>52.5009</TrainLatitude>
    <TrainLongitude>-8.20003</TrainLongitude>
    <TrainCode>A401</TrainCode>
    <TrainDate>03 Oct 2025</TrainDate>
    <PublicMessage>A401\n05:25 - Limerick to Dublin Heuston (0 mins late)\nDeparted Limerick Junction next stop Thurles</PublicMessage>
    <Direction>To Dublin Heuston</Direction>
  </objTrainPositions>
  <objTrainPositions>
    <TrainStatus>R</TrainStatus>
    <TrainLatitude>53.163</TrainLatitude>
    <TrainLongitude>-6.90802</TrainLongitude>
    <TrainCode>P200</TrainCode>
    <TrainDate>03 Oct 2025</TrainDate>
    <PublicMessage>P200\n05:30 - Portlaoise to Dublin Heuston (0 mins late)\nDeparted Kildare next stop Newbridge</PublicMessage>
    <Direction>To Dublin Heuston</Direction>
  </objTrainPositions>
  <objTrainPositions>
    <TrainStatus>R</TrainStatus>
    <TrainLatitude>53.2135</TrainLatitude>
    <TrainLongitude>-7.35205</TrainLongitude>
    <TrainCode>A701</TrainCode>
    <TrainDate>03 Oct 2025</TrainDate>
    <PublicMessage>A701\n05:20 - Athlone to Dublin Heuston (0 mins late)\nDeparted Geashill next stop Portarlington</PublicMessage>
    <Direction>To Dublin Heuston</Direction>
  </objTrainPositions>
  <objTrainPositions>
    <TrainStatus>R</TrainStatus>
    <TrainLatitude>53.2364</TrainLatitude>
    <TrainLongitude>-6.11691</TrainLongitude>
    <TrainCode>E901</TrainCode>
    <TrainDate>03 Oct 2025</TrainDate>
    <PublicMessage>E901\n05:39 - Greystones to Howth (0 mins late)\nDeparted Shankill next stop Killiney</PublicMessage>
    <Direction>Northbound</Direction>
  </objTrainPositions>
  <objTrainPositions>
    <TrainStatus>R</TrainStatus>
    <TrainLatitude>53.2991</TrainLatitude>
    <TrainLongitude>-6.16512</TrainLongitude>
    <TrainCode>E800</TrainCode>
    <TrainDate>03 Oct 2025</TrainDate>
    <PublicMessage>E800\n05:32 - Bray to Malahide (0 mins late)\nArrived Seapoint next stop Blackrock</PublicMessage>
    <Direction>Northbound</Direction>
  </objTrainPositions>
  <objTrainPositions>
    <TrainStatus>R</TrainStatus>
    <TrainLatitude>53.3223</TrainLatitude>
    <TrainLongitude>-6.52356</TrainLongitude>
    <TrainCode>A700</TrainCode>
    <TrainDate>03 Oct 2025</TrainDate>
    <PublicMessage>A700\n05:45 - Dublin Heuston to Galway (1 mins late)\nDeparted Hazelhatch next stop Newbridge</PublicMessage>
    <Direction>To Galway</Direction>
  </objTrainPositions>
  <objTrainPositions>
    <TrainStatus>R</TrainStatus>
    <TrainLatitude>53.3334</TrainLatitude>
    <TrainLongitude>-6.40628</TrainLongitude>
    <TrainCode>A225</TrainCode>
    <TrainDate>03 Oct 2025</TrainDate>
    <PublicMessage>A225\n17:25 - Cork to Dublin Heuston (18 mins late)\nDeparted Clondalkin next stop Dublin Heuston</PublicMessage>
    <Direction>To Dublin Heuston</Direction>
  </objTrainPositions>
  <objTrainPositions>
    <TrainStatus>R</TrainStatus>
    <TrainLatitude>53.3334</TrainLatitude>
    <TrainLongitude>-6.40628</TrainLongitude>
    <TrainCode>A227</TrainCode>
    <TrainDate>03 Oct 2025</TrainDate>
    <PublicMessage>A227\n18:25 - Cork to Dublin Heuston (22 mins late)\nDeparted Clondalkin next stop Dublin Heuston</PublicMessage>
    <Direction>To Dublin Heuston</Direction>
  </objTrainPositions>
  <objTrainPositions>
    <TrainStatus>R</TrainStatus>
    <TrainLatitude>53.3334</TrainLatitude>
    <TrainLongitude>-6.40628</TrainLongitude>
    <TrainCode>A229</TrainCode>
    <TrainDate>03 Oct 2025</TrainDate>
    <PublicMessage>A229\n19:25 - Cork to Dublin Heuston (22 mins late)\nDeparted Clondalkin next stop Dublin Heuston</PublicMessage>
    <Direction>To Dublin Heuston</Direction>
  </objTrainPositions>
  <objTrainPositions>
    <TrainStatus>R</TrainStatus>
    <TrainLatitude>53.3334</TrainLatitude>
    <TrainLongitude>-6.40628</TrainLongitude>
    <TrainCode>A231</TrainCode>
    <TrainDate>03 Oct 2025</TrainDate>
    <PublicMessage>A231\n20:25 - Cork to Dublin Heuston (10 mins late)\nDeparted Clondalkin next stop Dublin Heuston</PublicMessage>
    <Direction>To Dublin Heuston</Direction>
  </objTrainPositions>
  <objTrainPositions>
    <TrainStatus>R</TrainStatus>
    <TrainLatitude>53.3334</TrainLatitude>
    <TrainLongitude>-6.40628</TrainLongitude>
    <TrainCode>A527</TrainCode>
    <TrainDate>03 Oct 2025</TrainDate>
    <PublicMessage>A527\n18:25 - Waterford to Dublin Heuston (21 mins late)\nDeparted Clondalkin next stop Dublin Heuston</PublicMessage>
    <Direction>To Dublin Heuston</Direction>
  </objTrainPositions>
  <objTrainPositions>
    <TrainStatus>R</TrainStatus>
    <TrainLatitude>53.3704</TrainLatitude>
    <TrainLongitude>-6.50598</TrainLongitude>
    <TrainCode>D900</TrainCode>
    <TrainDate>03 Oct 2025</TrainDate>
    <PublicMessage>D900\n05:20 - Dublin Connolly to Maynooth (0 mins late)\nArrived Leixlip (Louisa Bridge) next stop Maynooth</PublicMessage>
    <Direction>Northbound</Direction>
  </objTrainPositions>
  <objTrainPositions>
    <TrainStatus>R</TrainStatus>
    <TrainLatitude>53.3704</TrainLatitude>
    <TrainLongitude>-6.50598</TrainLongitude>
    <TrainCode>P740</TrainCode>
    <TrainDate>03 Oct 2025</TrainDate>
    <PublicMessage>P740\n05:54 - Maynooth to Dublin Connolly (-2 mins late)\nArrived Leixlip (Louisa Bridge) next stop Leixlip (Confey)</PublicMessage>
    <Direction>Southbound</Direction>
  </objTrainPositions>
  <objTrainPositions>
    <TrainStatus>R</TrainStatus>
    <TrainLatitude>53.3786</TrainLatitude>
    <TrainLongitude>-6.19131</TrainLongitude>
    <TrainCode>A100</TrainCode>
    <TrainDate>03 Oct 2025</TrainDate>
    <PublicMessage>A100\n05:50 - Dublin Connolly to Belfast (0 mins late)\nArrived Harmonstown next stop Drogheda</PublicMessage>
    <Direction>Northbound</Direction>
  </objTrainPositions>
  <objTrainPositions>
    <TrainStatus>R</TrainStatus>
    <TrainLatitude>53.3891</TrainLatitude>
    <TrainLongitude>-6.07401</TrainLongitude>
    <TrainCode>E201</TrainCode>
    <TrainDate>03 Oct 2025</TrainDate>
    <PublicMessage>E201\n05:57 - Howth to Bray (1 mins late)\nDeparted Howth next stop Sutton</PublicMessage>
    <Direction>Southbound</Direction>
  </objTrainPositions>
  <objTrainPositions>
    <TrainStatus>R</TrainStatus>
    <TrainLatitude>53.6794</TrainLatitude>
    <TrainLongitude>-6.24253</TrainLongitude>
    <TrainCode>P600</TrainCode>
    <TrainDate>03 Oct 2025</TrainDate>
    <PublicMessage>P600\n05:27 - Dundalk to Grand Canal Dock (0 mins late)\nArrived Laytown next stop Balbriggan</PublicMessage>
    <Direction>To Grand Canal Dock</Direction>
  </objTrainPositions>
  <objTrainPositions>
    <TrainStatus>R</TrainStatus>
    <TrainLatitude>53.6888</TrainLatitude>
    <TrainLongitude>-7.60299</TrainLongitude>
    <TrainCode>P651</TrainCode>
    <TrainDate>03 Oct 2025</TrainDate>
    <PublicMessage>P651\n05:35 - Longford to Dublin Pearse (0 mins late)\nDeparted Edgeworthstown next stop Mullingar</PublicMessage>
    <Direction>Southbound</Direction>
  </objTrainPositions>
  <objTrainPositions>
    <TrainStatus>R</TrainStatus>
    <TrainLatitude>54.0887</TrainLatitude>
    <TrainLongitude>-8.52088</TrainLongitude>
    <TrainCode>A901</TrainCode>
    <TrainDate>03 Oct 2025</TrainDate>
    <PublicMessage>A901\n05:40 - Sligo to Dublin Connolly (0 mins late)\nArrived Ballymote next stop Boyle</PublicMessage>
    <Direction>Southbound</Direction>
  </objTrainPositions>
</ArrayOfObjTrainPositions>